overdue/__init__.py
overdue/action.py
overdue/py.typed
overdue/stopper.py
overdue-0.1.5.dist-info/METADATA
overdue-0.1.5.dist-info/WHEEL
overdue-0.1.5.dist-info/RECORD
