Metadata-Version: 2.4
Name: overdue
Version: 0.1.5
Summary: Easy timeout actions for any Python code with contextmanagers or decorators
Project-URL: source, https://github.com/kajaste/overdue
Author-email: Antti Kajander <9019523+kajaste@users.noreply.github.com>
License: MIT License
Keywords: error-handling,exception,performance,scalability,timeout
Requires-Python: >=3.10
